kagiso_search/__init__.py
kagiso_search/utils.py
kagiso_search/views.py
kagiso_search/migrations/0001_fts_index.py
kagiso_search/migrations/__init__.py
kagiso_search/tests/__init__.py
kagiso_search/tests/test_utils.py
kagiso_search/tests/urls.py
kagiso_search/tests/settings/__init__.py
kagiso_search/tests/settings/test.py
kagiso_search-3.1.0.dist-info/DESCRIPTION.rst
kagiso_search-3.1.0.dist-info/METADATA
kagiso_search-3.1.0.dist-info/RECORD
kagiso_search-3.1.0.dist-info/WHEEL
kagiso_search-3.1.0.dist-info/metadata.json
kagiso_search-3.1.0.dist-info/top_level.txt
