Metadata-Version: 2.0
Name: kagiso-search
Version: 3.1.0
Summary: Kagiso Search
Home-page: https://github.com/Kagiso-Future-Media/kagiso_search
Author: Kagiso Media
Author-email: development@kagiso.io
License: UNKNOWN
Platform: UNKNOWN
Requires-Dist: wagtail (>=1.8.0)
